codemach/__init__.py
codemach-0.3.dist-info/DESCRIPTION.rst
codemach-0.3.dist-info/METADATA
codemach-0.3.dist-info/RECORD
codemach-0.3.dist-info/WHEEL
codemach-0.3.dist-info/metadata.json
codemach-0.3.dist-info/top_level.txt
