Metadata-Version: 2.0
Name: codemach
Version: 0.3
Summary: very simple tool for executing python code objects
Home-page: http://github.com/chuck1/codemach
Author: Charles Rymal
Author-email: charlesrymal@gmail.com
License: MIT
Platform: UNKNOWN
Requires-Dist: Babel (==2.4.0)
Requires-Dist: Jinja2 (==2.9.6)
Requires-Dist: MarkupSafe (==1.0)
Requires-Dist: Pygments (==2.2.0)
Requires-Dist: Sphinx (==1.6.2)
Requires-Dist: alabaster (==0.7.10)
Requires-Dist: certifi (==2017.4.17)
Requires-Dist: chardet (==3.0.4)
Requires-Dist: coverage (==4.4.1)
Requires-Dist: docutils (==0.13.1)
Requires-Dist: idna (==2.5)
Requires-Dist: imagesize (==0.7.1)
Requires-Dist: pkgtool (==0.1b52)
Requires-Dist: py (==1.4.34)
Requires-Dist: pytest (==3.1.2)
Requires-Dist: pytest-cov (==2.5.1)
Requires-Dist: pytz (==2017.2)
Requires-Dist: requests (==2.18.1)
Requires-Dist: six (==1.10.0)
Requires-Dist: snowballstemmer (==1.2.1)
Requires-Dist: sphinxcontrib-websupport (==1.0.1)
Requires-Dist: termcolor (==1.1.0)
Requires-Dist: toml (==0.9.2)
Requires-Dist: urllib3 (==1.21.1)
